{
  "blockProps": {
    "titleStyle": {
      "component": "h2",
      "sx": {
        "typography": "subtitle1"
      }
    },
    "contentStyle": {
      "sx": {
        "p": 0
      }
    },
    "headerStyle": {
      "dividerVariant": "0",
      "sx": {
        "pt": 1,
        "pb": 1
      }
    },
    "footerStyle": {
      "dividerVariant": "0",
      "sx": {
        "mt": 2
      }
    },
    "blockStyle": {
      "sx": {
        "bgcolor": "0",
        "borderRadius": "0",
        "mt": 2,
        "mb": 2
      }
    }
  },
  "noHeader": 0,
  "noFooter": 0,
  "info": {
    "bundle": "web",
    "name": "App List - Sub Tab"
  }
}