{
  "large": {
    "blocks": [
      {
        "blockId": "12srw",
        "component": "activity-point.block.package",
        "slotName": "main",
        "title": "point_packages",
        "blockLayout": "App List"
      },
      {
        "blockId": "ia",
        "component": "core.block.sideAppHeader",
        "slotName": "side",
        "title": "activity_points",
        "icon": "ico-compose-alt",
        "blockLayout": "sidebar app header",
        "freeze": true
      },
      {
        "component": "core.block.sidebarAppMenu",
        "slotName": "side",
        "title": "activity_points",
        "blockId": "i8"
      }
    ],
    "pageName": "activity_point.packages",
    "templateName": "two-column-fixed"
  },
  "small": {
    "blocks": [
      {
        "component": "core.block.sidebarAppMobile",
        "slotName": "main",
        "blockProps": {
          "variant": "plained",
          "marginBottom": 2
        },
        "contents": [
          {
            "name": "core.block.sidebarAppMenu"
          },
          {
            "name": "core.categoryBlock"
          }
        ],
        "blockId": "ks3wd"
      },
      {
        "blockId": "12srw",
        "component": "activity-point.block.package",
        "slotName": "main",
        "title": "point_packages",
        "blockLayout": "App List - Mobile"
      }
    ],
    "containers": {},
    "templateName": "mobile"
  },
  "info": {
    "bundle": "web",
    "name": "activity_point.packages"
  }
}
